README.md
curljson.py
setup.py
curljson.egg-info/PKG-INFO
curljson.egg-info/SOURCES.txt
curljson.egg-info/dependency_links.txt
curljson.egg-info/entry_points.txt
curljson.egg-info/top_level.txt