Metadata-Version: 1.0
Name: curljson
Version: 0.9.8
Summary: curl with pretty json outputs
Home-page: https://github.com/mitnk/curljson
Author: mitnk
Author-email: w@mitnk.com
License: MIT
Keywords: curl json pretty
Platform: UNKNOWN
